trafolta/__init__.py
trafolta/chtrans.py
trafolta/wgsconv.py
trafolta-0.0.1.dist-info/LICENSE
trafolta-0.0.1.dist-info/METADATA
trafolta-0.0.1.dist-info/WHEEL
trafolta-0.0.1.dist-info/top_level.txt
trafolta-0.0.1.dist-info/RECORD
