Metadata-Version: 2.1
Name: trafolta
Version: 0.0.1
Summary: Coordinate Transformations for Swiss Reference Systems
Home-page: https://github.com/eraymann/trafolta
Author: Elias Raymann
Author-email: elias.raymann@swisstopo.ch
License: UNKNOWN
Platform: UNKNOWN
Classifier: Development Status :: 4 - Beta
Classifier: Programming Language :: Python :: 3.6
Classifier: License :: OSI Approved :: MIT License
Classifier: Operating System :: OS Independent
Requires-Python: >=2.7
